univorm/__init__.py
univorm/db.py
univorm/parser.py
univorm/reader/__init__.py
univorm/reader/nosql.py
univorm/reader/sql.py
univorm/writer/__init__.py
univorm/writer/nosql.py
univorm/writer/sql.py
univorm-0.5.0.dist-info/WHEEL
univorm-0.5.0.dist-info/METADATA
univorm-0.5.0.dist-info/RECORD
