Metadata-Version: 2.3
Name: univorm
Version: 0.5.0
Summary: One ORM Wrapper to Rule Them All
Author: Masum Billal
Author-email: Masum Billal <billalmasum93@gmail.com>
License:                                  Apache License
Requires-Dist: aiomysql>=0.2.0
Requires-Dist: asyncpg>=0.29.0
Requires-Dist: mypy>=1.11.2
Requires-Dist: pymssql>=2.3.1
Requires-Dist: sqlalchemy>=2.0.35
Requires-Dist: pydantic>=2.9.2
Requires-Dist: polars>=1.8.2
Requires-Dist: pandas>=2.2.3
Requires-Dist: cryptography>=43.0.1
Requires-Dist: pandas-stubs>=2.2.2.240909
Requires-Dist: pyarrow>=17.0.0
Requires-Dist: pymongo[encryption,ocsp,snappy]>=4.11.3
Requires-Dist: python-dotenv>=1.1.1
Requires-Dist: furo>=2024.8.6 ; extra == 'docs'
Requires-Dist: pydata-sphinx-theme>=0.15.4 ; extra == 'docs'
Requires-Dist: sphinx>=8.0.2 ; extra == 'docs'
Requires-Dist: pre-commit>=3.8.0 ; extra == 'formatting'
Requires-Python: >=3.12
Provides-Extra: docs
Provides-Extra: formatting
